MANIFEST.in
README
setup.py
attributes/__init__.py
attributes/admin.py
attributes/models.py
attributes/utils.py
django_attributes.egg-info/PKG-INFO
django_attributes.egg-info/SOURCES.txt
django_attributes.egg-info/dependency_links.txt
django_attributes.egg-info/top_level.txt
django_attributes.egg-info/zip-safe